{"name":"shining-star","maxBlock":5,"BPM":104,"offset":0,"notes":[{"LPB":6,"num":12,"block":0,"type":1,"notes":[]},{"LPB":12,"num":72,"block":1,"type":1,"notes":[]},{"LPB":12,"num":88,"block":2,"type":1,"notes":[]},{"LPB":12,"num":134,"block":3,"type":1,"notes":[]},{"LPB":6,"num":83,"block":0,"type":1,"notes":[]},{"LPB":12,"num":214,"block":3,"type":1,"notes":[]},{"LPB":12,"num":230,"block":3,"type":1,"notes":[]},{"LPB":12,"num":261,"block":0,"type":1,"notes":[]},{"LPB":12,"num":277,"block":0,"type":1,"notes":[]},{"LPB":12,"num":308,"block":1,"type":1,"notes":[]},{"LPB":12,"num":324,"block":1,"type":1,"notes":[]},{"LPB":12,"num":347,"block":0,"type":1,"notes":[]},{"LPB":12,"num":359,"block":0,"type":1,"notes":[]},{"LPB":12,"num":368,"block":2,"type":1,"notes":[]},{"LPB":12,"num":375,"block":2,"type":1,"notes":[]},{"LPB":12,"num":395,"block":0,"type":1,"notes":[]},{"LPB":12,"num":419,"block":2,"type":1,"notes":[]},{"LPB":12,"num":450,"block":0,"type":1,"notes":[]},{"LPB":12,"num":478,"block":2,"type":1,"notes":[]},{"LPB":12,"num":530,"block":1,"type":1,"notes":[]},{"LPB":12,"num":546,"block":3,"type":1,"notes":[]},{"LPB":12,"num":577,"block":1,"type":1,"notes":[]},{"LPB":12,"num":604,"block":3,"type":1,"notes":[]},{"LPB":12,"num":627,"block":1,"type":1,"notes":[]},{"LPB":12,"num":631,"block":1,"type":1,"notes":[]},{"LPB":4,"num":216,"block":0,"type":1,"notes":[]},{"LPB":12,"num":672,"block":1,"type":1,"notes":[]},{"LPB":12,"num":702,"block":2,"type":1,"notes":[]},{"LPB":4,"num":240,"block":0,"type":1,"notes":[]},{"LPB":4,"num":243,"block":0,"type":1,"notes":[]},{"LPB":4,"num":246,"block":0,"type":1,"notes":[]},{"LPB":4,"num":249,"block":0,"type":1,"notes":[]},{"LPB":12,"num":765,"block":3,"type":1,"notes":[]},{"LPB":12,"num":783,"block":3,"type":1,"notes":[]},{"LPB":12,"num":798,"block":3,"type":1,"notes":[]},{"LPB":12,"num":818,"block":2,"type":1,"notes":[]},{"LPB":12,"num":826,"block":2,"type":1,"notes":[]},{"LPB":12,"num":844,"block":3,"type":1,"notes":[]},{"LPB":12,"num":864,"block":0,"type":1,"notes":[]},{"LPB":12,"num":902,"block":0,"type":1,"notes":[]},{"LPB":12,"num":913,"block":0,"type":1,"notes":[]},{"LPB":12,"num":917,"block":0,"type":1,"notes":[]},{"LPB":12,"num":924,"block":0,"type":1,"notes":[]},{"LPB":12,"num":932,"block":0,"type":1,"notes":[]},{"LPB":12,"num":937,"block":0,"type":1,"notes":[]},{"LPB":12,"num":944,"block":0,"type":1,"notes":[]},{"LPB":12,"num":949,"block":0,"type":1,"notes":[]},{"LPB":12,"num":964,"block":3,"type":1,"notes":[]},{"LPB":12,"num":975,"block":3,"type":1,"notes":[]},{"LPB":12,"num":979,"block":3,"type":1,"notes":[]},{"LPB":12,"num":987,"block":3,"type":1,"notes":[]},{"LPB":12,"num":995,"block":3,"type":1,"notes":[]},{"LPB":12,"num":1000,"block":3,"type":1,"notes":[]},{"LPB":12,"num":1006,"block":3,"type":1,"notes":[]},{"LPB":12,"num":1011,"block":3,"type":1,"notes":[]},{"LPB":12,"num":1036,"block":0,"type":1,"notes":[]},{"LPB":12,"num":1052,"block":1,"type":1,"notes":[]},{"LPB":12,"num":1067,"block":2,"type":1,"notes":[]},{"LPB":12,"num":1082,"block":0,"type":1,"notes":[]},{"LPB":12,"num":1097,"block":1,"type":1,"notes":[]},{"LPB":12,"num":1113,"block":2,"type":1,"notes":[]},{"LPB":12,"num":1129,"block":0,"type":1,"notes":[]},{"LPB":12,"num":1145,"block":1,"type":1,"notes":[]},{"LPB":12,"num":1160,"block":2,"type":1,"notes":[]},{"LPB":12,"num":1175,"block":3,"type":1,"notes":[]},{"LPB":12,"num":1193,"block":0,"type":1,"notes":[]},{"LPB":12,"num":1209,"block":0,"type":1,"notes":[]},{"LPB":12,"num":1220,"block":0,"type":1,"notes":[]},{"LPB":12,"num":1224,"block":0,"type":1,"notes":[]},{"LPB":12,"num":1239,"block":0,"type":1,"notes":[]},{"LPB":12,"num":1256,"block":1,"type":1,"notes":[]},{"LPB":12,"num":1271,"block":1,"type":1,"notes":[]},{"LPB":12,"num":1283,"block":1,"type":1,"notes":[]},{"LPB":12,"num":1287,"block":1,"type":1,"notes":[]},{"LPB":12,"num":1303,"block":1,"type":1,"notes":[]},{"LPB":12,"num":1319,"block":2,"type":1,"notes":[]},{"LPB":12,"num":1335,"block":2,"type":1,"notes":[]},{"LPB":12,"num":1347,"block":2,"type":1,"notes":[]},{"LPB":12,"num":1351,"block":2,"type":1,"notes":[]},{"LPB":12,"num":1367,"block":2,"type":1,"notes":[]},{"LPB":12,"num":1382,"block":3,"type":1,"notes":[]},{"LPB":12,"num":1398,"block":3,"type":1,"notes":[]},{"LPB":12,"num":1410,"block":3,"type":1,"notes":[]},{"LPB":12,"num":1414,"block":3,"type":1,"notes":[]},{"LPB":12,"num":1431,"block":0,"type":1,"notes":[]},{"LPB":12,"num":1438,"block":1,"type":1,"notes":[]},{"LPB":12,"num":1446,"block":0,"type":1,"notes":[]},{"LPB":12,"num":1462,"block":1,"type":1,"notes":[]},{"LPB":12,"num":1470,"block":2,"type":1,"notes":[]},{"LPB":12,"num":1478,"block":1,"type":1,"notes":[]},{"LPB":12,"num":1493,"block":2,"type":1,"notes":[]},{"LPB":12,"num":1501,"block":3,"type":1,"notes":[]},{"LPB":12,"num":1509,"block":2,"type":1,"notes":[]},{"LPB":12,"num":1524,"block":2,"type":1,"notes":[]},{"LPB":12,"num":1532,"block":3,"type":1,"notes":[]},{"LPB":12,"num":1541,"block":2,"type":1,"notes":[]},{"LPB":12,"num":1556,"block":1,"type":1,"notes":[]},{"LPB":12,"num":1564,"block":2,"type":1,"notes":[]},{"LPB":12,"num":1572,"block":1,"type":1,"notes":[]},{"LPB":12,"num":1589,"block":0,"type":1,"notes":[]},{"LPB":12,"num":1597,"block":1,"type":1,"notes":[]},{"LPB":12,"num":1604,"block":0,"type":1,"notes":[]},{"LPB":12,"num":1620,"block":0,"type":1,"notes":[]},{"LPB":12,"num":1635,"block":2,"type":1,"notes":[]},{"LPB":12,"num":1643,"block":2,"type":1,"notes":[]},{"LPB":12,"num":1651,"block":2,"type":1,"notes":[]},{"LPB":12,"num":1683,"block":0,"type":1,"notes":[]},{"LPB":12,"num":1698,"block":0,"type":1,"notes":[]},{"LPB":12,"num":1715,"block":0,"type":1,"notes":[]},{"LPB":12,"num":1745,"block":3,"type":1,"notes":[]},{"LPB":12,"num":1749,"block":3,"type":1,"notes":[]}]}